mktimeline/__init__.py
mktimeline/console/__init__.py
mktimeline/console/application.py
mktimeline/console/commands/__init__.py
mktimeline/console/commands/about.py
mktimeline/console/commands/build.py
mktimeline/console/commands/export_timeline.py
mktimeline/console/commands/import_timeline.py
mktimeline/console/commands/init.py
mktimeline/events/__init__.py
mktimeline/events/event.py
mktimeline/templates/__init__.py
mktimeline/templates/template.html
mktimeline/timeline/__init__.py
mktimeline/timeline/project.py
mktimeline-0.1.3.dist-info/LICENSE
mktimeline-0.1.3.dist-info/WHEEL
mktimeline-0.1.3.dist-info/entry_points.txt
mktimeline-0.1.3.dist-info/METADATA
mktimeline-0.1.3.dist-info/RECORD
